Metadata-Version: 2.1
Name: xdataforge
Version: 0.1.0
Requires-Dist: requests
